logparser/__init__.py
logparser/version.py
logparser/AEL/AEL.py
logparser/AEL/__init__.py
logparser/AEL/benchmark.py
logparser/AEL/demo.py
logparser/Brain/Brain.py
logparser/Brain/__init__.py
logparser/Brain/benchmark.py
logparser/Brain/demo.py
logparser/Drain/Drain.py
logparser/Drain/__init__.py
logparser/Drain/benchmark.py
logparser/Drain/demo.py
logparser/IPLoM/IPLoM.py
logparser/IPLoM/__init__.py
logparser/IPLoM/benchmark.py
logparser/IPLoM/demo.py
logparser/LFA/LFA.py
logparser/LFA/__init__.py
logparser/LFA/benchmark.py
logparser/LFA/demo.py
logparser/LKE/LKE.py
logparser/LKE/__init__.py
logparser/LKE/benchmark.py
logparser/LKE/demo.py
logparser/LenMa/__init__.py
logparser/LenMa/benchmark.py
logparser/LenMa/demo.py
logparser/LenMa/src/LenMa.py
logparser/LenMa/src/__init__.py
logparser/LenMa/src/lenma_template.py
logparser/LenMa/src/template.py
logparser/LogCluster/__init__.py
logparser/LogCluster/benchmark.py
logparser/LogCluster/demo.py
logparser/LogCluster/src/LogCluster.py
logparser/LogCluster/src/__init__.py
logparser/LogMine/__init__.py
logparser/LogMine/benchmark.py
logparser/LogMine/demo.py
logparser/LogMine/src/LogMine.py
logparser/LogMine/src/__init__.py
logparser/LogMine/src/alignment.py
logparser/LogSig/LogSig.py
logparser/LogSig/__init__.py
logparser/LogSig/benchmark.py
logparser/LogSig/demo.py
logparser/Logram/__init__.py
logparser/Logram/benchmark.py
logparser/Logram/demo.py
logparser/Logram/src/Common.py
logparser/Logram/src/DictionarySetUp.py
logparser/Logram/src/Logram.py
logparser/Logram/src/MatchToken.py
logparser/Logram/src/__init__.py
logparser/MoLFI/__init__.py
logparser/MoLFI/benchmark.py
logparser/MoLFI/demo.py
logparser/MoLFI/src/MoLFI.py
logparser/MoLFI/src/__init__.py
logparser/MoLFI/src/definitions.py
logparser/MoLFI/src/validation.py
logparser/MoLFI/src/main/__init__.py
logparser/MoLFI/src/main/org/__init__.py
logparser/MoLFI/src/main/org/core/__init__.py
logparser/MoLFI/src/main/org/core/chromosome/__init__.py
logparser3-1.0.4.dist-info/LICENSE.md
logparser3-1.0.4.dist-info/METADATA
logparser3-1.0.4.dist-info/WHEEL
logparser3-1.0.4.dist-info/top_level.txt
logparser3-1.0.4.dist-info/RECORD
